{
    "name":"Resistance",
    "type": "origins:multiple",
    "activate":
    {
        "type": "origins:action_on_callback",
        "entity_action_gained": {
            "type":"origins:and",
            "actions":[
                {
                    "type": "origins:execute_command",
                    "command": "effect give @s minecraft:resistance 7 0"
                },
                {
                    "type": "origins:execute_command",
                    "command": "particle minecraft:dust_color_transition 1 1 1 1 0.7 0.7 0.7 ~ ~1 ~ 0.5 0.5 0.5 1 100"
                },
                {
                    "type": "origins:execute_command",
                    "command": "particle minecraft:end_rod ~ ~1 ~ 0.5 0.5 0.5 0.1 10"
                },
                {
                    "type": "origins:execute_command",
                    "command": "playsound minecraft:entity.evoker.cast_spell player @s ~ ~ ~ 2 2"
                },
                {
                    "type": "origins:execute_command",
                    "command": "power remove @s hypno:playstyle/hephaestus/tanuki/chance"
                },
                {
                "type":"origins:delay",
                 "ticks":1,
                 "action":{
                    "type": "origins:execute_command",
                    "command": "power remove @s hypno:playstyle/hephaestus/tanuki/effects/resistance"
                }
                }
        ]
    },
        "execute_chosen_when_orb": false
    },
    "hidden": true
}